__init__.py
wintrymodels/__init__.py
wintrymodels/dbcontext.py
wintrymodels/transaction.py
wintrymodels-1.0.0.dist-info/LICENSE
wintrymodels-1.0.0.dist-info/METADATA
wintrymodels-1.0.0.dist-info/WHEEL
wintrymodels-1.0.0.dist-info/top_level.txt
wintrymodels-1.0.0.dist-info/RECORD
