Metadata-Version: 2.1
Name: wintrymodels
Version: 1.0.0
Summary: Integrates SQLModel with wintry framework
Author-email: Adrian Gonzalez <adriangonzalezsanchez1996@gmail.com>
License: MIT License        
Keywords: wintry,orm,sql
Classifier: License :: OSI Approved :: MIT License
Classifier: Programming Language :: Python
Classifier: Programming Language :: Python :: 3
Requires-Python: >=3.10
License-File: LICENSE
Requires-Dist: sqlmodel
Requires-Dist: wintry
Requires-Dist: tomli ; python_version < "3.11"
